naddrtools/__init__.py
naddrtools/naddrtools.py
tests/__init__.py
tests/test_naddrtools.py
naddrtools-0.1.2.dist-info/LICENSE
naddrtools-0.1.2.dist-info/METADATA
naddrtools-0.1.2.dist-info/WHEEL
naddrtools-0.1.2.dist-info/top_level.txt
naddrtools-0.1.2.dist-info/RECORD
