Metadata-Version: 2.1
Name: naddrtools
Version: 0.1.2
Summary: A module for manipulating IP addresses, ranges, and networks, supplementing the netaddr module.
Home-page: https://github.com/khantext/naddrtools
License: UNKNOWN
Project-URL: Bug Tracker, https://github.com/khantext/naddrtools/issues
Platform: UNKNOWN
Classifier: Programming Language :: Python :: 3
Classifier: License :: OSI Approved :: GNU Lesser General Public License v3 (LGPLv3)
Classifier: Operating System :: OS Independent
Requires-Python: >=3.6
Requires-Dist: netaddr
